nmigen_yosys/__init__.py
nmigen_yosys/__main__.py
nmigen_yosys/yosys.wasm
nmigen_yosys/share/include/backends/cxxrtl/cxxrtl.h
nmigen_yosys/share/include/backends/cxxrtl/cxxrtl_capi.cc
nmigen_yosys/share/include/backends/cxxrtl/cxxrtl_capi.h
nmigen_yosys/share/include/backends/cxxrtl/cxxrtl_vcd.h
nmigen_yosys/share/include/backends/cxxrtl/cxxrtl_vcd_capi.cc
nmigen_yosys/share/include/backends/cxxrtl/cxxrtl_vcd_capi.h
nmigen_yosys-0.9.post3746.dev38.dist-info/LICENSE.txt
nmigen_yosys-0.9.post3746.dev38.dist-info/METADATA
nmigen_yosys-0.9.post3746.dev38.dist-info/WHEEL
nmigen_yosys-0.9.post3746.dev38.dist-info/top_level.txt
nmigen_yosys-0.9.post3746.dev38.dist-info/RECORD
