Metadata-Version: 2.1
Name: nmigen-yosys
Version: 0.9.post3746.dev38
Summary: Specialized WebAssembly build of Yosys used by nMigen
Home-page: UNKNOWN
Author: whitequark
Author-email: whitequark@whitequark.org
License: ISC
Project-URL: Source Code, https://github.com/nmigen/nmigen-yosys
Project-URL: Bug Tracker, https://github.com/nmigen/nmigen-yosys/issues
Platform: UNKNOWN
Classifier: License :: OSI Approved :: ISC License (ISCL)
Requires-Python: ~=3.5
License-File: LICENSE.txt
Requires-Dist: wasmtime (<0.31,>=0.30)
Requires-Dist: importlib-resources (>=1.4) ; python_version < "3.7"
